indic_eval/__init__.py
indic_eval/data.py
indic_eval/evaluator.py
indic_eval/few_shot_manager.py
indic_eval/indic_accelerate.py
indic_eval/main_accelerate.py
indic_eval/main_nanotron.py
indic_eval/utils.py
indic_eval/utils_parallelism.py
indic_eval/logging/evaluation_tracker.py
indic_eval/logging/hierarchical_logger.py
indic_eval/logging/info_loggers.py
indic_eval/metrics/__init__.py
indic_eval/metrics/metrics.py
indic_eval/metrics/metrics_corpus.py
indic_eval/metrics/metrics_sample.py
indic_eval/metrics/normalizations.py
indic_eval/metrics/sample_preparator.py
indic_eval/metrics/stderr.py
indic_eval/metrics/utils.py
indic_eval/metrics/harness_compatibility/drop.py
indic_eval/metrics/harness_compatibility/truthful_qa.py
indic_eval/metrics/imports/bert_scorer.py
indic_eval/metrics/imports/data_stats_metric.py
indic_eval/metrics/imports/data_stats_utils.py
indic_eval/metrics/imports/summac.py
indic_eval/models/abstract_model.py
indic_eval/models/adapter_model.py
indic_eval/models/base_model.py
indic_eval/models/delta_model.py
indic_eval/models/endpoint_model.py
indic_eval/models/model_config.py
indic_eval/models/model_loader.py
indic_eval/models/model_output.py
indic_eval/models/nanotron_model.py
indic_eval/models/tgi_model.py
indic_eval/models/utils.py
indic_eval/tasks/indic_tasks_table.jsonl
indic_eval/tasks/lighteval_task.py
indic_eval/tasks/registry.py
indic_eval/tasks/requests.py
indic_eval/tasks/tasks_prompt_formatting.py
indic_eval/tasks/tasks_table.jsonl
indic_eval/tasks/extended/__init__.py
indic_eval/tasks/extended/ifeval/instructions.py
indic_eval/tasks/extended/ifeval/instructions_registry.py
indic_eval/tasks/extended/ifeval/instructions_utils.py
indic_eval/tasks/extended/ifeval/main.py
indic_eval/tasks/extended/tiny_benchmarks/main.py
indic_eval-0.1.0.dist-info/LICENSE
indic_eval-0.1.0.dist-info/METADATA
indic_eval-0.1.0.dist-info/WHEEL
indic_eval-0.1.0.dist-info/top_level.txt
indic_eval-0.1.0.dist-info/RECORD
