Metadata-Version: 2.1
Name: indic-eval
Version: 0.1.0
Summary: A package to make LLM evaluation easier
Author-email: Adithya S Kolavi <adithyaskolavi@gmail.com>
Maintainer-email: Adithya S Kolavi <adithyaskolavi@gmail.com>
License: MIT License
Project-URL: Homepage, https://github.com/adithya-s-k/indic_eval
Project-URL: Issues, https://github.com/adithya-s-k/indic_eval/issues
Keywords: evaluation,nlp,llm
Classifier: Programming Language :: Python :: 3
Classifier: License :: OSI Approved :: MIT License
Classifier: Operating System :: OS Independent
Requires-Python: >=3.10
License-File: LICENSE
Requires-Dist: art ==6.1
Requires-Dist: requests
Requires-Dist: transformers >=4.38.0
Requires-Dist: huggingface-hub >=0.22.0
Requires-Dist: torch >=2.0
Requires-Dist: GitPython >=3.1.41
Requires-Dist: datasets >=2.14.0
Requires-Dist: termcolor ==2.3.0
Requires-Dist: pytablewriter
Requires-Dist: colorama
Requires-Dist: aenum ==3.1.15
Requires-Dist: nltk ==3.8.1
Requires-Dist: scikit-learn
Requires-Dist: spacy ==3.7.2
Requires-Dist: sacrebleu
Requires-Dist: rouge-score ==0.1.2
Requires-Dist: sentencepiece >=0.1.99
Requires-Dist: protobuf ==3.20.*
Requires-Dist: pycountry
Provides-Extra: accelerate
Requires-Dist: accelerate ; extra == 'accelerate'
Provides-Extra: adapters
Requires-Dist: peft ==0.3.0 ; extra == 'adapters'
Provides-Extra: dev
Requires-Dist: indic-eval[accelerate,quality,tests] ; extra == 'dev'
Provides-Extra: extended_tasks
Requires-Dist: langdetect ; extra == 'extended_tasks'
Provides-Extra: nanotron
Requires-Dist: nanotron ; extra == 'nanotron'
Requires-Dist: tensorboardX ; extra == 'nanotron'
Provides-Extra: optimum
Requires-Dist: optimum ==1.12.0 ; extra == 'optimum'
Provides-Extra: quality
Requires-Dist: ruff ==v0.2.2 ; extra == 'quality'
Requires-Dist: pre-commit ; extra == 'quality'
Provides-Extra: quantization
Requires-Dist: bitsandbytes >=0.41.0 ; extra == 'quantization'
Requires-Dist: auto-gptq >=0.4.2 ; extra == 'quantization'
Provides-Extra: tests
Requires-Dist: pytest ==7.4.0 ; extra == 'tests'
Provides-Extra: tgi
Requires-Dist: text-generation ==0.6.0 ; extra == 'tgi'
